{"targets":[{"isStage":true,"name":"Stage","variables":{"`jEk@4|i[#Fk?(8x)AV.-my variable":["my variable",0]},"lists":{},"broadcasts":{},"blocks":{},"comments":{},"currentCostume":3,"costumes":[{"assetId":"cd21514d0531fdffb22204e0ec5ed84a","name":"backdrop1","md5ext":"cd21514d0531fdffb22204e0ec5ed84a.svg","dataFormat":"svg","rotationCenterX":240,"rotationCenterY":180},{"assetId":"da102a69d135973e0fc139131dec785a","name":"Hay Field","bitmapResolution":2,"md5ext":"da102a69d135973e0fc139131dec785a.png","dataFormat":"png","rotationCenterX":480,"rotationCenterY":360},{"assetId":"0c450891306fa63ef02aa0fda7fd0ef9","name":"Spaceship","bitmapResolution":2,"md5ext":"0c450891306fa63ef02aa0fda7fd0ef9.png","dataFormat":"png","rotationCenterX":480,"rotationCenterY":360},{"assetId":"d26cfd278999c9e37d6af75c296a58df","name":"Woods","bitmapResolution":1,"md5ext":"d26cfd278999c9e37d6af75c296a58df.svg","dataFormat":"svg","rotationCenterX":240,"rotationCenterY":180}],"sounds":[{"assetId":"83a9787d4cb6f3b7632b4ddfebf74367","name":"pop","dataFormat":"wav","format":"","rate":48000,"sampleCount":1123,"md5ext":"83a9787d4cb6f3b7632b4ddfebf74367.wav"}],"volume":100,"layerOrder":0,"tempo":60,"videoTransparency":50,"videoState":"on","textToSpeechLanguage":null},{"isStage":false,"name":"Wizard-toad","variables":{},"lists":{},"broadcasts":{},"blocks":{"%lnnDJr*ptDwpTZsCH%J":{"opcode":"event_whenthisspriteclicked","next":"hdl2dS-57piC|Ep.h((b","parent":null,"inputs":{},"fields":{},"shadow":false,"topLevel":true,"x":209,"y":163},"8;EEVh:w+xw3p{FZ2Skp":{"opcode":"looks_sayforsecs","next":"pQ/6OlNR7;h]j:Vd94WV","parent":"hdl2dS-57piC|Ep.h((b","inputs":{"MESSAGE":[1,[10,"You can be anything you want to be on Halloween"]],"SECS":[1,[4,"3"]]},"fields":{},"shadow":false,"topLevel":false},"hdl2dS-57piC|Ep.h((b":{"opcode":"looks_changesizeby","next":"8;EEVh:w+xw3p{FZ2Skp","parent":"%lnnDJr*ptDwpTZsCH%J","inputs":{"CHANGE":[1,[4,"60"]]},"fields":{},"shadow":false,"topLevel":false},"pQ/6OlNR7;h]j:Vd94WV":{"opcode":"looks_changesizeby","next":null,"parent":"8;EEVh:w+xw3p{FZ2Skp","inputs":{"CHANGE":[1,[4,"-60"]]},"fields":{},"shadow":false,"topLevel":false}},"comments":{},"currentCostume":0,"costumes":[{"assetId":"ca3bb4d397ecf6cda3edc48340af908b","name":"wizard-toad-a","bitmapResolution":1,"md5ext":"ca3bb4d397ecf6cda3edc48340af908b.svg","dataFormat":"svg","rotationCenterX":87,"rotationCenterY":80},{"assetId":"6181be2dc005eb73aa9d0e8201c6ea79","name":"wizard-toad-b","bitmapResolution":1,"md5ext":"6181be2dc005eb73aa9d0e8201c6ea79.svg","dataFormat":"svg","rotationCenterX":47.74155797300665,"rotationCenterY":37.40568084989846}],"sounds":[{"assetId":"1cb60ecdb1075c8769cb346d5c2a22c7","name":"Magic Spell","dataFormat":"wav","format":"adpcm","rate":22050,"sampleCount":43689,"md5ext":"1cb60ecdb1075c8769cb346d5c2a22c7.wav"},{"assetId":"c6ce0aadb89903a43f76fc20ea57633e","name":"croak","dataFormat":"wav","format":"adpcm","rate":22050,"sampleCount":7113,"md5ext":"c6ce0aadb89903a43f76fc20ea57633e.wav"}],"volume":100,"layerOrder":2,"visible":true,"x":156.00000000000003,"y":-117,"size":69,"direction":90,"draggable":false,"rotationStyle":"all around"},{"isStage":false,"name":"Bat","variables":{},"lists":{},"broadcasts":{},"blocks":{"X@{V_:Fh},#Q-=icM34H":{"opcode":"event_whenthisspriteclicked","next":")n?1J_Bv93g1?@Xb(ukT","parent":null,"inputs":{},"fields":{},"shadow":false,"topLevel":true,"x":100,"y":114},"BSD(DFz*KVkFAf*yU$RL":{"opcode":"looks_sayforsecs","next":"aZRgw|Q:3@JSEyG4QH?!","parent":")n?1J_Bv93g1?@Xb(ukT","inputs":{"MESSAGE":[1,[10,"People give out free candy!"]],"SECS":[1,[4,"2"]]},"fields":{},"shadow":false,"topLevel":false},"aZRgw|Q:3@JSEyG4QH?!":{"opcode":"looks_sayforsecs","next":"L5Y];vK1P9{oX%clEnm6","parent":"BSD(DFz*KVkFAf*yU$RL","inputs":{"MESSAGE":[1,[10,"I know it's hard to believe"]],"SECS":[1,[4,"2"]]},"fields":{},"shadow":false,"topLevel":false},")n?1J_Bv93g1?@Xb(ukT":{"opcode":"looks_changesizeby","next":"BSD(DFz*KVkFAf*yU$RL","parent":"X@{V_:Fh},#Q-=icM34H","inputs":{"CHANGE":[1,[4,"60"]]},"fields":{},"shadow":false,"topLevel":false},"L5Y];vK1P9{oX%clEnm6":{"opcode":"looks_changesizeby","next":null,"parent":"aZRgw|Q:3@JSEyG4QH?!","inputs":{"CHANGE":[1,[4,"-60"]]},"fields":{},"shadow":false,"topLevel":false}},"comments":{},"currentCostume":0,"costumes":[{"assetId":"4e4ced87ed37ee66c758bba077e0eae6","name":"bat-a","bitmapResolution":1,"md5ext":"4e4ced87ed37ee66c758bba077e0eae6.svg","dataFormat":"svg","rotationCenterX":80,"rotationCenterY":60},{"assetId":"bc6dd12fc9e407c7774959cdf427f8b5","name":"bat-b","bitmapResolution":1,"md5ext":"bc6dd12fc9e407c7774959cdf427f8b5.svg","dataFormat":"svg","rotationCenterX":39,"rotationCenterY":61},{"assetId":"60f5bfce5d9b11bfcd199a6aa5454b3f","name":"bat-c","bitmapResolution":1,"md5ext":"60f5bfce5d9b11bfcd199a6aa5454b3f.svg","dataFormat":"svg","rotationCenterX":68,"rotationCenterY":66},{"assetId":"698c2a48e774f9959d57c9618b156c20","name":"bat-d","bitmapResolution":1,"md5ext":"698c2a48e774f9959d57c9618b156c20.svg","dataFormat":"svg","rotationCenterX":29,"rotationCenterY":62}],"sounds":[{"assetId":"e8b6d605f5a1bb36c29e4e21ef754209","name":"owl","dataFormat":"wav","format":"","rate":48000,"sampleCount":35313,"md5ext":"e8b6d605f5a1bb36c29e4e21ef754209.wav"}],"volume":100,"layerOrder":4,"visible":true,"x":164.99999999999997,"y":103,"size":69,"direction":90,"draggable":false,"rotationStyle":"all around"},{"isStage":false,"name":"Goblin","variables":{},"lists":{},"broadcasts":{},"blocks":{"qloYBY{M6?:A+;c9r-_/":{"opcode":"event_whenthisspriteclicked","next":"}B./kfU.hnIe=+amj]$w","parent":null,"inputs":{},"fields":{},"shadow":false,"topLevel":true,"x":140,"y":141},"7WRz-H`wv$_a~gbovr_U":{"opcode":"looks_sayforsecs","next":"OelKBNJAiD(V!ict``;)","parent":"}B./kfU.hnIe=+amj]$w","inputs":{"MESSAGE":[1,[10,"people dress up every year for halloween"]],"SECS":[1,[4,"2"]]},"fields":{},"shadow":false,"topLevel":false},"OelKBNJAiD(V!ict``;)":{"opcode":"looks_sayforsecs","next":"k5RQRA1nHc6x[`,7]JP4","parent":"7WRz-H`wv$_a~gbovr_U","inputs":{"MESSAGE":[1,[10,"Can you believe Halloween was around for years"]],"SECS":[1,[4,"3"]]},"fields":{},"shadow":false,"topLevel":false},"}B./kfU.hnIe=+amj]$w":{"opcode":"looks_changesizeby","next":"7WRz-H`wv$_a~gbovr_U","parent":"qloYBY{M6?:A+;c9r-_/","inputs":{"CHANGE":[1,[4,"60"]]},"fields":{},"shadow":false,"topLevel":false},"k5RQRA1nHc6x[`,7]JP4":{"opcode":"looks_changesizeby","next":null,"parent":"OelKBNJAiD(V!ict``;)","inputs":{"CHANGE":[1,[4,"-60"]]},"fields":{},"shadow":false,"topLevel":false}},"comments":{},"currentCostume":0,"costumes":[{"assetId":"516de3e8f595a033468e28d48f69c639","name":"goblin-a","bitmapResolution":1,"md5ext":"516de3e8f595a033468e28d48f69c639.svg","dataFormat":"svg","rotationCenterX":25.743040000000008,"rotationCenterY":77.69390000000001},{"assetId":"b8604b8039d6b633015aaf17d74d5d5b","name":"goblin-b","bitmapResolution":1,"md5ext":"b8604b8039d6b633015aaf17d74d5d5b.svg","dataFormat":"svg","rotationCenterX":40,"rotationCenterY":80},{"assetId":"afb9fe328adae617ee3375366fca02e7","name":"goblin-d","bitmapResolution":1,"md5ext":"afb9fe328adae617ee3375366fca02e7.svg","dataFormat":"svg","rotationCenterX":40,"rotationCenterY":80},{"assetId":"2add9ef4eaa25f8915406dcfd8bafc9f","name":"goblin-c","bitmapResolution":1,"md5ext":"2add9ef4eaa25f8915406dcfd8bafc9f.svg","dataFormat":"svg","rotationCenterX":40,"rotationCenterY":80}],"sounds":[{"assetId":"b92de59d992a655c1b542223a784cda6","name":"fairydust","dataFormat":"wav","format":"","rate":48000,"sampleCount":24483,"md5ext":"b92de59d992a655c1b542223a784cda6.wav"}],"volume":100,"layerOrder":3,"visible":true,"x":18.000000000000014,"y":-14.000000000000007,"size":120,"direction":90,"draggable":false,"rotationStyle":"all around"},{"isStage":false,"name":"Dragon","variables":{},"lists":{},"broadcasts":{},"blocks":{"Rz|7n=Ynou:*92/o%yn)":{"opcode":"looks_sayforsecs","next":"^*Z(HMa)0q^4Q-nrK^Yg","parent":"D:.2]vPJ_7`umJ7tnmlH","inputs":{"MESSAGE":[1,[10,"People go out to trick or treat"]],"SECS":[1,[4,"2"]]},"fields":{},"shadow":false,"topLevel":false},"^*Z(HMa)0q^4Q-nrK^Yg":{"opcode":"looks_sayforsecs","next":"}*Zj+UNZK}CyE+WZMCc0","parent":"Rz|7n=Ynou:*92/o%yn)","inputs":{"MESSAGE":[1,[10,"Halloween is so much fun "]],"SECS":[1,[4,"2"]]},"fields":{},"shadow":false,"topLevel":false},"D:.2]vPJ_7`umJ7tnmlH":{"opcode":"looks_changesizeby","next":"Rz|7n=Ynou:*92/o%yn)","parent":"24LT}{0qTf(^DX^9lrBD","inputs":{"CHANGE":[1,[4,"60"]]},"fields":{},"shadow":false,"topLevel":false},"ylf[}/EK3lt!!62unn5g":{"opcode":"looks_changesizeby","next":null,"parent":"}*Zj+UNZK}CyE+WZMCc0","inputs":{"CHANGE":[1,[4,"-60"]]},"fields":{},"shadow":false,"topLevel":false},"24LT}{0qTf(^DX^9lrBD":{"opcode":"event_whenflagclicked","next":"D:.2]vPJ_7`umJ7tnmlH","parent":null,"inputs":{},"fields":{},"shadow":false,"topLevel":true,"x":102,"y":72},"}*Zj+UNZK}CyE+WZMCc0":{"opcode":"looks_sayforsecs","next":"ylf[}/EK3lt!!62unn5g","parent":"^*Z(HMa)0q^4Q-nrK^Yg","inputs":{"MESSAGE":[1,[10,"Click on the Sprites to learn more about them"]],"SECS":[1,[4,"2"]]},"fields":{},"shadow":false,"topLevel":false}},"comments":{},"currentCostume":0,"costumes":[{"assetId":"a166d123597ed8896cfb7c397a9fc9c4","name":"dragon-a","bitmapResolution":1,"md5ext":"a166d123597ed8896cfb7c397a9fc9c4.svg","dataFormat":"svg","rotationCenterX":210,"rotationCenterY":150},{"assetId":"235f7a2f17fce30bd3c9cb7360c87994","name":"dragon-b","bitmapResolution":1,"md5ext":"235f7a2f17fce30bd3c9cb7360c87994.svg","dataFormat":"svg","rotationCenterX":210,"rotationCenterY":150},{"assetId":"3a6ff36986f85e6d005cfc65d9eb4978","name":"dragon-c","bitmapResolution":1,"md5ext":"3a6ff36986f85e6d005cfc65d9eb4978.svg","dataFormat":"svg","rotationCenterX":210,"rotationCenterY":150}],"sounds":[{"assetId":"1cb60ecdb1075c8769cb346d5c2a22c7","name":"Magic Spell","dataFormat":"wav","format":"adpcm","rate":22050,"sampleCount":43689,"md5ext":"1cb60ecdb1075c8769cb346d5c2a22c7.wav"}],"volume":100,"layerOrder":1,"visible":true,"x":-250,"y":-101.00000000000001,"size":100,"direction":90,"draggable":false,"rotationStyle":"all around"}],"monitors":[],"extensions":[],"meta":{"semver":"3.0.0","vm":"0.2.0-prerelease.20190430163103","agent":"Mozilla/5.0 (Windows NT 10.0; Win64; x64) AppleWebKit/537.36 (KHTML, like Gecko) Chrome/73.0.3683.86 Safari/537.36"}}