{"targets":[{"isStage":true,"name":"Stage","variables":{},"lists":{},"broadcasts":{},"blocks":{},"comments":{},"currentCostume":2,"costumes":[{"assetId":"797b03bdb8cf6ccfc30c0692d533d998","name":"backdrop1","bitmapResolution":2,"md5ext":"797b03bdb8cf6ccfc30c0692d533d998.png","dataFormat":"png","rotationCenterX":480,"rotationCenterY":360},{"assetId":"0b4a15ba028bf205ec051390d6ac4de7","name":"metro1","bitmapResolution":2,"md5ext":"0b4a15ba028bf205ec051390d6ac4de7.png","dataFormat":"png","rotationCenterX":480,"rotationCenterY":360},{"assetId":"d26bf4c3980163d9106625cc2ea6c50d","name":"spotlight-stage","bitmapResolution":2,"md5ext":"d26bf4c3980163d9106625cc2ea6c50d.png","dataFormat":"png","rotationCenterX":480,"rotationCenterY":360},{"assetId":"efb625f7e0b199b15f69e116cd053cea","name":"berkeley mural","bitmapResolution":2,"md5ext":"efb625f7e0b199b15f69e116cd053cea.png","dataFormat":"png","rotationCenterX":480,"rotationCenterY":360},{"assetId":"92bb5e11aee1e29cd312d6099b33dd9b","name":"stage2","bitmapResolution":2,"md5ext":"92bb5e11aee1e29cd312d6099b33dd9b.png","dataFormat":"png","rotationCenterX":480,"rotationCenterY":360}],"sounds":[{"assetId":"83a9787d4cb6f3b7632b4ddfebf74367","name":"pop","dataFormat":"wav","format":"","rate":44100,"sampleCount":1032,"md5ext":"83a9787d4cb6f3b7632b4ddfebf74367.wav"}],"volume":100,"layerOrder":0,"tempo":60,"videoTransparency":50,"videoState":"off","textToSpeechLanguage":null},{"isStage":false,"name":"Anina","variables":{},"lists":{},"broadcasts":{},"blocks":{"LRUgDrIkI)7p8qETGRe-":{"opcode":"event_whenthisspriteclicked","next":"OKVN:J!RhkkQo},/pp~T","parent":null,"inputs":{},"fields":{},"shadow":false,"topLevel":true,"x":49,"y":66},"+67,7)Q(~Rj-fMim[=u{":{"opcode":"control_wait","next":"o@NZepfe9Kmeqm=JcL{M","parent":"OKVN:J!RhkkQo},/pp~T","inputs":{"DURATION":[1,[5,"0.2"]]},"fields":{},"shadow":false,"topLevel":false},"XkR,bzjw;~S![$B7~KID":{"opcode":"control_wait","next":"ZMBJG4]{N3zjLz*gT,Y5","parent":"G3n;c]uKj8Ec]HHB=Yrl","inputs":{"DURATION":[1,[5,"0.2"]]},"fields":{},"shadow":false,"topLevel":false},"}[c3+C(L3yE2nI0!Y^6W":{"opcode":"control_wait","next":"tZ,E?`nCi~,,e!H;DmCz","parent":"o@NZepfe9Kmeqm=JcL{M","inputs":{"DURATION":[1,[5,"0.2"]]},"fields":{},"shadow":false,"topLevel":false},"}e$j%q*ZsVe:NF%)NAXs":{"opcode":"control_wait","next":"G3n;c]uKj8Ec]HHB=Yrl","parent":"tZ,E?`nCi~,,e!H;DmCz","inputs":{"DURATION":[1,[5,"0.2"]]},"fields":{},"shadow":false,"topLevel":false},"OKVN:J!RhkkQo},/pp~T":{"opcode":"looks_switchcostumeto","next":"+67,7)Q(~Rj-fMim[=u{","parent":"LRUgDrIkI)7p8qETGRe-","inputs":{"COSTUME":[1,"Y|ss3OM_VsqMoVn,T*1h"]},"fields":{},"shadow":false,"topLevel":false},"Y|ss3OM_VsqMoVn,T*1h":{"opcode":"looks_costume","next":null,"parent":"OKVN:J!RhkkQo},/pp~T","inputs":{},"fields":{"COSTUME":["anina stance",null]},"shadow":true,"topLevel":false},"o@NZepfe9Kmeqm=JcL{M":{"opcode":"looks_switchcostumeto","next":"}[c3+C(L3yE2nI0!Y^6W","parent":"+67,7)Q(~Rj-fMim[=u{","inputs":{"COSTUME":[1,"=BQA`VNw$?o~^UJ^MXhu"]},"fields":{},"shadow":false,"topLevel":false},"=BQA`VNw$?o~^UJ^MXhu":{"opcode":"looks_costume","next":null,"parent":"o@NZepfe9Kmeqm=JcL{M","inputs":{},"fields":{"COSTUME":["anina top stand",null]},"shadow":true,"topLevel":false},"UV^u()fQk.a{UX@bfHZ8":{"opcode":"control_wait","next":"ShZK15AGpkA:yJ@KgUGP","parent":"ZMBJG4]{N3zjLz*gT,Y5","inputs":{"DURATION":[1,[5,"0.2"]]},"fields":{},"shadow":false,"topLevel":false},"tZ,E?`nCi~,,e!H;DmCz":{"opcode":"looks_switchcostumeto","next":"}e$j%q*ZsVe:NF%)NAXs","parent":"}[c3+C(L3yE2nI0!Y^6W","inputs":{"COSTUME":[1,"MH3)+HA_%6cmW$;N#I@|"]},"fields":{},"shadow":false,"topLevel":false},"MH3)+HA_%6cmW$;N#I@|":{"opcode":"looks_costume","next":null,"parent":"tZ,E?`nCi~,,e!H;DmCz","inputs":{},"fields":{"COSTUME":["anina top R step",null]},"shadow":true,"topLevel":false},"G3n;c]uKj8Ec]HHB=Yrl":{"opcode":"looks_switchcostumeto","next":"XkR,bzjw;~S![$B7~KID","parent":"}e$j%q*ZsVe:NF%)NAXs","inputs":{"COSTUME":[1,",hL^HH`x$Y%}!modW_ZI"]},"fields":{},"shadow":false,"topLevel":false},",hL^HH`x$Y%}!modW_ZI":{"opcode":"looks_costume","next":null,"parent":"G3n;c]uKj8Ec]HHB=Yrl","inputs":{},"fields":{"COSTUME":["anina top L step",null]},"shadow":true,"topLevel":false},"ZMBJG4]{N3zjLz*gT,Y5":{"opcode":"looks_switchcostumeto","next":"UV^u()fQk.a{UX@bfHZ8","parent":"XkR,bzjw;~S![$B7~KID","inputs":{"COSTUME":[1,"ei*ZOl:-9n65s*8m7VY5"]},"fields":{},"shadow":false,"topLevel":false},"ei*ZOl:-9n65s*8m7VY5":{"opcode":"looks_costume","next":null,"parent":"ZMBJG4]{N3zjLz*gT,Y5","inputs":{},"fields":{"COSTUME":["anina top freeze",null]},"shadow":true,"topLevel":false},"ShZK15AGpkA:yJ@KgUGP":{"opcode":"looks_switchcostumeto","next":"H|7SStG5+oB[e)}Zvez0","parent":"UV^u()fQk.a{UX@bfHZ8","inputs":{"COSTUME":[1,"b}DlI!:8X|sR/@CzyRE8"]},"fields":{},"shadow":false,"topLevel":false},"b}DlI!:8X|sR/@CzyRE8":{"opcode":"looks_costume","next":null,"parent":"ShZK15AGpkA:yJ@KgUGP","inputs":{},"fields":{"COSTUME":["anina R cross",null]},"shadow":true,"topLevel":false},";J!m|7FzJtuJ={v7aD?|":{"opcode":"looks_switchcostumeto","next":"[gaMViqf4m+HZe)yv+[|","parent":"H|7SStG5+oB[e)}Zvez0","inputs":{"COSTUME":[1,"H]3i`5y6];5/q5G2cTLq"]},"fields":{},"shadow":false,"topLevel":false},"H]3i`5y6];5/q5G2cTLq":{"opcode":"looks_costume","next":null,"parent":";J!m|7FzJtuJ={v7aD?|","inputs":{},"fields":{"COSTUME":["anina pop front",null]},"shadow":true,"topLevel":false},":$Z~?Se(^R;rH5oz_?xC":{"opcode":"looks_switchcostumeto","next":"lph4VUjZJqudF%o39y(4","parent":"[gaMViqf4m+HZe)yv+[|","inputs":{"COSTUME":[1,"AM+6,AnKx}ACQ;NmI|o="]},"fields":{},"shadow":false,"topLevel":false},"AM+6,AnKx}ACQ;NmI|o=":{"opcode":"looks_costume","next":null,"parent":":$Z~?Se(^R;rH5oz_?xC","inputs":{},"fields":{"COSTUME":["anina pop down",null]},"shadow":true,"topLevel":false},"=yWoX)4WKGp,wdZ8YG!u":{"opcode":"looks_switchcostumeto","next":"AM(Gf(:CQQTd[=8T11{B","parent":"lph4VUjZJqudF%o39y(4","inputs":{"COSTUME":[1,"1fGivyX9PL9H^S$!C=+F"]},"fields":{},"shadow":false,"topLevel":false},"1fGivyX9PL9H^S$!C=+F":{"opcode":"looks_costume","next":null,"parent":"=yWoX)4WKGp,wdZ8YG!u","inputs":{},"fields":{"COSTUME":["anina pop left",null]},"shadow":true,"topLevel":false},"H|7SStG5+oB[e)}Zvez0":{"opcode":"control_wait","next":";J!m|7FzJtuJ={v7aD?|","parent":"ShZK15AGpkA:yJ@KgUGP","inputs":{"DURATION":[1,[5,"0.2"]]},"fields":{},"shadow":false,"topLevel":false},"[gaMViqf4m+HZe)yv+[|":{"opcode":"control_wait","next":":$Z~?Se(^R;rH5oz_?xC","parent":";J!m|7FzJtuJ={v7aD?|","inputs":{"DURATION":[1,[5,"0.2"]]},"fields":{},"shadow":false,"topLevel":false},"lph4VUjZJqudF%o39y(4":{"opcode":"control_wait","next":"=yWoX)4WKGp,wdZ8YG!u","parent":":$Z~?Se(^R;rH5oz_?xC","inputs":{"DURATION":[1,[5,"0.2"]]},"fields":{},"shadow":false,"topLevel":false},"AM(Gf(:CQQTd[=8T11{B":{"opcode":"control_wait","next":"+06/m$(#Whv1$[MvGVdi","parent":"=yWoX)4WKGp,wdZ8YG!u","inputs":{"DURATION":[1,[5,"0.2"]]},"fields":{},"shadow":false,"topLevel":false},"+06/m$(#Whv1$[MvGVdi":{"opcode":"looks_switchcostumeto","next":null,"parent":"AM(Gf(:CQQTd[=8T11{B","inputs":{"COSTUME":[1,"SIp#{NhmCm2GB.mXX~@2"]},"fields":{},"shadow":false,"topLevel":false},"SIp#{NhmCm2GB.mXX~@2":{"opcode":"looks_costume","next":null,"parent":"+06/m$(#Whv1$[MvGVdi","inputs":{},"fields":{"COSTUME":["anina stance",null]},"shadow":true,"topLevel":false}},"comments":{},"currentCostume":0,"costumes":[{"assetId":"d50bf14d40e3cbd0847ab5d8c6e835f0","name":"anina stance","bitmapResolution":2,"md5ext":"d50bf14d40e3cbd0847ab5d8c6e835f0.png","dataFormat":"png","rotationCenterX":246,"rotationCenterY":252},{"assetId":"db6c03113f71b91f22a9f3351f90e5bf","name":"anina top stand","bitmapResolution":2,"md5ext":"db6c03113f71b91f22a9f3351f90e5bf.png","dataFormat":"png","rotationCenterX":74,"rotationCenterY":280},{"assetId":"2d208a34e74fdce9dab9d4c585dcfa2b","name":"anina top R step","bitmapResolution":2,"md5ext":"2d208a34e74fdce9dab9d4c585dcfa2b.png","dataFormat":"png","rotationCenterX":248,"rotationCenterY":272},{"assetId":"ed90e8b7a05c1552194af597ac0637cd","name":"anina top L step","bitmapResolution":2,"md5ext":"ed90e8b7a05c1552194af597ac0637cd.png","dataFormat":"png","rotationCenterX":228,"rotationCenterY":274},{"assetId":"a1c9b65dd07747964cce642f9099921b","name":"anina top freeze","bitmapResolution":2,"md5ext":"a1c9b65dd07747964cce642f9099921b.png","dataFormat":"png","rotationCenterX":110,"rotationCenterY":268},{"assetId":"22f3ca23b2f0ac67f8ebc36a8c3116a0","name":"anina R cross","bitmapResolution":2,"md5ext":"22f3ca23b2f0ac67f8ebc36a8c3116a0.png","dataFormat":"png","rotationCenterX":126,"rotationCenterY":268},{"assetId":"c163f1002f61421816386e52522b9133","name":"anina pop front","bitmapResolution":2,"md5ext":"c163f1002f61421816386e52522b9133.png","dataFormat":"png","rotationCenterX":68,"rotationCenterY":270},{"assetId":"e9e54ff1fa61c71507e25540d0326177","name":"anina pop down","bitmapResolution":2,"md5ext":"e9e54ff1fa61c71507e25540d0326177.png","dataFormat":"png","rotationCenterX":74,"rotationCenterY":156},{"assetId":"9fda30f66d51b2ad5f6fe11d57e199d6","name":"anina pop left","bitmapResolution":2,"md5ext":"9fda30f66d51b2ad5f6fe11d57e199d6.png","dataFormat":"png","rotationCenterX":238,"rotationCenterY":266},{"assetId":"cc2594e9278494e82f725be34369f178","name":"anina pop right","bitmapResolution":2,"md5ext":"cc2594e9278494e82f725be34369f178.png","dataFormat":"png","rotationCenterX":66,"rotationCenterY":268},{"assetId":"843bff4a5ee3d61fd8cbd419cb2797a3","name":"anina pop L arm","bitmapResolution":2,"md5ext":"843bff4a5ee3d61fd8cbd419cb2797a3.png","dataFormat":"png","rotationCenterX":68,"rotationCenterY":274},{"assetId":"de7cab2c8d567d49a5a1f378b5709bb4","name":"anina pop stand","bitmapResolution":2,"md5ext":"de7cab2c8d567d49a5a1f378b5709bb4.png","dataFormat":"png","rotationCenterX":76,"rotationCenterY":276},{"assetId":"e7e1a86233b7ad28d6ee9970b152be20","name":"anina pop R arm","bitmapResolution":2,"md5ext":"e7e1a86233b7ad28d6ee9970b152be20.png","dataFormat":"png","rotationCenterX":88,"rotationCenterY":272}],"sounds":[{"assetId":"0edb8fb88af19e6e17d0f8cf64c1d136","name":"dance celebrate","dataFormat":"wav","format":"adpcm","rate":22050,"sampleCount":176785,"md5ext":"0edb8fb88af19e6e17d0f8cf64c1d136.wav"}],"volume":100,"layerOrder":2,"visible":true,"x":-100,"y":-55,"size":80,"direction":90.06743321270105,"draggable":false,"rotationStyle":"left-right"},{"isStage":false,"name":"Breakdancer","variables":{},"lists":{},"broadcasts":{},"blocks":{"c{.BKH{18`JqTT1GC8W}":{"opcode":"looks_switchcostumeto","next":"Q,IgPP!TNv=gwfofEFY6","parent":"s^~0*,K0w]N`y_iC`h}-","inputs":{"COSTUME":[1,".M[p!}BNC=DL36-Y*T(4"]},"fields":{},"shadow":false,"topLevel":false},".M[p!}BNC=DL36-Y*T(4":{"opcode":"looks_costume","next":null,"parent":"c{.BKH{18`JqTT1GC8W}","inputs":{},"fields":{"COSTUME":["breakdancer1-a",null]},"shadow":true,"topLevel":false},"Q3bvC]PT|6p|jcWmha~f":{"opcode":"looks_switchcostumeto","next":"Gmh?,Xdy;FS-bi6TwUMd","parent":"Q,IgPP!TNv=gwfofEFY6","inputs":{"COSTUME":[1,"ASs9+x+A=czEeGqJ8dnf"]},"fields":{},"shadow":false,"topLevel":false},"ASs9+x+A=czEeGqJ8dnf":{"opcode":"looks_costume","next":null,"parent":"Q3bvC]PT|6p|jcWmha~f","inputs":{},"fields":{"COSTUME":["breakdancer1-b",null]},"shadow":true,"topLevel":false},"!01SJ$uYjY24gBo2$LjA":{"opcode":"looks_switchcostumeto","next":":9:M;k9`lU_40]%DO~(V","parent":"Gmh?,Xdy;FS-bi6TwUMd","inputs":{"COSTUME":[1,"KM3N-=?(~bTvZNA]Oh$!"]},"fields":{},"shadow":false,"topLevel":false},"KM3N-=?(~bTvZNA]Oh$!":{"opcode":"looks_costume","next":null,"parent":"!01SJ$uYjY24gBo2$LjA","inputs":{},"fields":{"COSTUME":["breakdancer1-c",null]},"shadow":true,"topLevel":false},"s^~0*,K0w]N`y_iC`h}-":{"opcode":"control_repeat","next":null,"parent":"#U}0*`sWP6bVHb20tdMz","inputs":{"TIMES":[1,[6,"3"]],"SUBSTACK":[2,"c{.BKH{18`JqTT1GC8W}"]},"fields":{},"shadow":false,"topLevel":false},"Q,IgPP!TNv=gwfofEFY6":{"opcode":"control_wait","next":"Q3bvC]PT|6p|jcWmha~f","parent":"c{.BKH{18`JqTT1GC8W}","inputs":{"DURATION":[1,[5,"0.2"]]},"fields":{},"shadow":false,"topLevel":false},"Gmh?,Xdy;FS-bi6TwUMd":{"opcode":"control_wait","next":"!01SJ$uYjY24gBo2$LjA","parent":"Q3bvC]PT|6p|jcWmha~f","inputs":{"DURATION":[1,[5,"0.2"]]},"fields":{},"shadow":false,"topLevel":false},":9:M;k9`lU_40]%DO~(V":{"opcode":"control_wait","next":null,"parent":"!01SJ$uYjY24gBo2$LjA","inputs":{"DURATION":[1,[5,"0.2"]]},"fields":{},"shadow":false,"topLevel":false},"#U}0*`sWP6bVHb20tdMz":{"opcode":"event_whenthisspriteclicked","next":"s^~0*,K0w]N`y_iC`h}-","parent":null,"inputs":{},"fields":{},"shadow":false,"topLevel":true,"x":-13,"y":-951}},"comments":{},"currentCostume":2,"costumes":[{"assetId":"3af0f08e9212a134ff2bbf96adbfda48","name":"breakdancer1-a","bitmapResolution":2,"md5ext":"3af0f08e9212a134ff2bbf96adbfda48.png","dataFormat":"png","rotationCenterX":226,"rotationCenterY":180},{"assetId":"218efbcab88cf36f2dbf1a23303ef4b6","name":"breakdancer1-b","bitmapResolution":2,"md5ext":"218efbcab88cf36f2dbf1a23303ef4b6.png","dataFormat":"png","rotationCenterX":60,"rotationCenterY":180},{"assetId":"2a958fd5c082a6391fd81c04d6f7d1d1","name":"breakdancer1-c","bitmapResolution":2,"md5ext":"2a958fd5c082a6391fd81c04d6f7d1d1.png","dataFormat":"png","rotationCenterX":66,"rotationCenterY":178}],"sounds":[{"assetId":"83a9787d4cb6f3b7632b4ddfebf74367","name":"pop","dataFormat":"wav","format":"","rate":44100,"sampleCount":1032,"md5ext":"83a9787d4cb6f3b7632b4ddfebf74367.wav"}],"volume":100,"layerOrder":1,"visible":true,"x":143.2,"y":-70,"size":100,"direction":90,"draggable":false,"rotationStyle":"all around"},{"isStage":false,"name":"Khalid","variables":{},"lists":{},"broadcasts":{},"blocks":{"HBovsR2@i]oKBKJ|khrF":{"opcode":"event_whenthisspriteclicked","next":"!qvW.6m7nRf2:a}pWDa|","parent":null,"inputs":{},"fields":{},"shadow":false,"topLevel":true,"x":37,"y":76},"!qvW.6m7nRf2:a}pWDa|":{"opcode":"looks_switchcostumeto","next":"gcbac-=N/4:G+U^N[gOy","parent":"HBovsR2@i]oKBKJ|khrF","inputs":{"COSTUME":[1,"7/~8A,:bnxwwRy(ub[Bt"]},"fields":{},"shadow":false,"topLevel":false},"7/~8A,:bnxwwRy(ub[Bt":{"opcode":"looks_costume","next":null,"parent":"!qvW.6m7nRf2:a}pWDa|","inputs":{},"fields":{"COSTUME":["khalid-a",null]},"shadow":true,"topLevel":false},"gcbac-=N/4:G+U^N[gOy":{"opcode":"control_repeat","next":null,"parent":"!qvW.6m7nRf2:a}pWDa|","inputs":{"TIMES":[1,[6,"2"]],"SUBSTACK":[2,";w9R=n4U[u4}D-9l79hg"]},"fields":{},"shadow":false,"topLevel":false},"M9kXux6r,%DfxNkwvWR!":{"opcode":"control_wait","next":"$+vcj_@l_6]ox-B(3ANq","parent":";w9R=n4U[u4}D-9l79hg","inputs":{"DURATION":[1,[5,"0.2"]]},"fields":{},"shadow":false,"topLevel":false},";w9R=n4U[u4}D-9l79hg":{"opcode":"looks_switchcostumeto","next":"M9kXux6r,%DfxNkwvWR!","parent":"gcbac-=N/4:G+U^N[gOy","inputs":{"COSTUME":[1,"P/bEE0xYmzH6wLTU`sb9"]},"fields":{},"shadow":false,"topLevel":false},"P/bEE0xYmzH6wLTU`sb9":{"opcode":"looks_costume","next":null,"parent":";w9R=n4U[u4}D-9l79hg","inputs":{},"fields":{"COSTUME":["Khalid-b",null]},"shadow":true,"topLevel":false},"$+vcj_@l_6]ox-B(3ANq":{"opcode":"looks_switchcostumeto","next":",;A/h(5LE|L$tB5ED45g","parent":"M9kXux6r,%DfxNkwvWR!","inputs":{"COSTUME":[1,"FZ|=w@~cfZm-X|R}Lg-V"]},"fields":{},"shadow":false,"topLevel":false},"FZ|=w@~cfZm-X|R}Lg-V":{"opcode":"looks_costume","next":null,"parent":"$+vcj_@l_6]ox-B(3ANq","inputs":{},"fields":{"COSTUME":["khalid-c",null]},"shadow":true,"topLevel":false},",;A/h(5LE|L$tB5ED45g":{"opcode":"control_wait","next":"KAt$/lY)c{N48G8V/KI3","parent":"$+vcj_@l_6]ox-B(3ANq","inputs":{"DURATION":[1,[5,"0.2"]]},"fields":{},"shadow":false,"topLevel":false},"KAt$/lY)c{N48G8V/KI3":{"opcode":"looks_switchcostumeto","next":"69ox9%xgqMb9tM9@}8p?","parent":",;A/h(5LE|L$tB5ED45g","inputs":{"COSTUME":[1,"KP^_O7~qAu}uZ5F!0o8@"]},"fields":{},"shadow":false,"topLevel":false},"KP^_O7~qAu}uZ5F!0o8@":{"opcode":"looks_costume","next":null,"parent":"KAt$/lY)c{N48G8V/KI3","inputs":{},"fields":{"COSTUME":["khalid-d",null]},"shadow":true,"topLevel":false},"Xka;X6AHm({FEbnC~0/,":{"opcode":"looks_switchcostumeto","next":"TQlxdI16N+P6zD,ZFXD@","parent":"69ox9%xgqMb9tM9@}8p?","inputs":{"COSTUME":[1,"tzn:~!R!)}Wu~Jt/#[LO"]},"fields":{},"shadow":false,"topLevel":false},"tzn:~!R!)}Wu~Jt/#[LO":{"opcode":"looks_costume","next":null,"parent":"Xka;X6AHm({FEbnC~0/,","inputs":{},"fields":{"COSTUME":["khalid-a",null]},"shadow":true,"topLevel":false},"69ox9%xgqMb9tM9@}8p?":{"opcode":"control_wait","next":"Xka;X6AHm({FEbnC~0/,","parent":"KAt$/lY)c{N48G8V/KI3","inputs":{"DURATION":[1,[5,"0.2"]]},"fields":{},"shadow":false,"topLevel":false},"TQlxdI16N+P6zD,ZFXD@":{"opcode":"control_wait","next":null,"parent":"Xka;X6AHm({FEbnC~0/,","inputs":{"DURATION":[1,[5,"0.2"]]},"fields":{},"shadow":false,"topLevel":false}},"comments":{},"currentCostume":0,"costumes":[{"assetId":"1e8844a43e15fa3c62a04cd4564eea54","name":"khalid-a","bitmapResolution":2,"md5ext":"1e8844a43e15fa3c62a04cd4564eea54.png","dataFormat":"png","rotationCenterX":79,"rotationCenterY":101},{"assetId":"88023269142bfc3ecab5b13cc8cbddb9","name":"Khalid-b","bitmapResolution":2,"md5ext":"88023269142bfc3ecab5b13cc8cbddb9.png","dataFormat":"png","rotationCenterX":69,"rotationCenterY":103},{"assetId":"30dbce950a2d2dddc0ea53d1462d116b","name":"khalid-c","bitmapResolution":2,"md5ext":"30dbce950a2d2dddc0ea53d1462d116b.png","dataFormat":"png","rotationCenterX":69,"rotationCenterY":109},{"assetId":"e189aec22f4cb57a90f75457615fbbd8","name":"khalid-d","bitmapResolution":2,"md5ext":"e189aec22f4cb57a90f75457615fbbd8.png","dataFormat":"png","rotationCenterX":66,"rotationCenterY":63}],"sounds":[{"assetId":"83a9787d4cb6f3b7632b4ddfebf74367","name":"pop","dataFormat":"wav","format":"","rate":44100,"sampleCount":1032,"md5ext":"83a9787d4cb6f3b7632b4ddfebf74367.wav"}],"volume":100,"layerOrder":3,"visible":true,"x":-5,"y":0,"size":100,"direction":90,"draggable":false,"rotationStyle":"all around"},{"isStage":false,"name":"Ballerina","variables":{},"lists":{},"broadcasts":{},"blocks":{"0YjrU86!e|0Y9:=*1o@#":{"opcode":"event_whenthisspriteclicked","next":"mVEw;3gBFTJ*d_Q|o%Gb","parent":null,"inputs":{},"fields":{},"shadow":false,"topLevel":true,"x":-2,"y":44},":[!CYM8!_CL`vN1`OC(r":{"opcode":"control_repeat","next":null,"parent":"mVEw;3gBFTJ*d_Q|o%Gb","inputs":{"TIMES":[1,[6,"2"]],"SUBSTACK":[2,"x5ajMR6wf*_fV@U@y-#;"]},"fields":{},"shadow":false,"topLevel":false},"mVEw;3gBFTJ*d_Q|o%Gb":{"opcode":"looks_switchcostumeto","next":":[!CYM8!_CL`vN1`OC(r","parent":"0YjrU86!e|0Y9:=*1o@#","inputs":{"COSTUME":[1,"`x9.2ZW,/PJgB_U;EbHm"]},"fields":{},"shadow":false,"topLevel":false},"`x9.2ZW,/PJgB_U;EbHm":{"opcode":"looks_costume","next":null,"parent":"mVEw;3gBFTJ*d_Q|o%Gb","inputs":{},"fields":{"COSTUME":["ballerina-a",null]},"shadow":true,"topLevel":false},"x5ajMR6wf*_fV@U@y-#;":{"opcode":"looks_switchcostumeto","next":"MOSz;tO@5=a,PwO))ab[","parent":":[!CYM8!_CL`vN1`OC(r","inputs":{"COSTUME":[1,"Yi2u#lzE9-eA*0@33wf="]},"fields":{},"shadow":false,"topLevel":false},"Yi2u#lzE9-eA*0@33wf=":{"opcode":"looks_costume","next":null,"parent":"x5ajMR6wf*_fV@U@y-#;","inputs":{},"fields":{"COSTUME":["ballerina-b",null]},"shadow":true,"topLevel":false},"l#g[,8/X/]jtU(e=f~xL":{"opcode":"looks_switchcostumeto","next":"FpHjTya^6KSd`%F~qEY^","parent":"MOSz;tO@5=a,PwO))ab[","inputs":{"COSTUME":[1,"teC8;ppv]WS@.7KqXMeK"]},"fields":{},"shadow":false,"topLevel":false},"teC8;ppv]WS@.7KqXMeK":{"opcode":"looks_costume","next":null,"parent":"l#g[,8/X/]jtU(e=f~xL","inputs":{},"fields":{"COSTUME":["ballerina-c",null]},"shadow":true,"topLevel":false},"7zUHDuzx6A+*AWw!G~+n":{"opcode":"looks_switchcostumeto","next":"3-I*JzA[H/`GZ]`^Nt6]","parent":"FpHjTya^6KSd`%F~qEY^","inputs":{"COSTUME":[1,"7i-MI7*FU#wM7CAJ:zo,"]},"fields":{},"shadow":false,"topLevel":false},"7i-MI7*FU#wM7CAJ:zo,":{"opcode":"looks_costume","next":null,"parent":"7zUHDuzx6A+*AWw!G~+n","inputs":{},"fields":{"COSTUME":["ballerina-d",null]},"shadow":true,"topLevel":false},"%R)9:Xk-@-=M:l:,t~X#":{"opcode":"looks_switchcostumeto","next":"Qk+}!6az9,|Tn%bT%v?@","parent":"3-I*JzA[H/`GZ]`^Nt6]","inputs":{"COSTUME":[1,"e5#yxpKWy+,S*jEVU5vk"]},"fields":{},"shadow":false,"topLevel":false},"e5#yxpKWy+,S*jEVU5vk":{"opcode":"looks_costume","next":null,"parent":"%R)9:Xk-@-=M:l:,t~X#","inputs":{},"fields":{"COSTUME":["ballerina-a",null]},"shadow":true,"topLevel":false},"MOSz;tO@5=a,PwO))ab[":{"opcode":"control_wait","next":"l#g[,8/X/]jtU(e=f~xL","parent":"x5ajMR6wf*_fV@U@y-#;","inputs":{"DURATION":[1,[5,"0.2"]]},"fields":{},"shadow":false,"topLevel":false},"FpHjTya^6KSd`%F~qEY^":{"opcode":"control_wait","next":"7zUHDuzx6A+*AWw!G~+n","parent":"l#g[,8/X/]jtU(e=f~xL","inputs":{"DURATION":[1,[5,"0.2"]]},"fields":{},"shadow":false,"topLevel":false},"3-I*JzA[H/`GZ]`^Nt6]":{"opcode":"control_wait","next":"%R)9:Xk-@-=M:l:,t~X#","parent":"7zUHDuzx6A+*AWw!G~+n","inputs":{"DURATION":[1,[5,"0.2"]]},"fields":{},"shadow":false,"topLevel":false},"Qk+}!6az9,|Tn%bT%v?@":{"opcode":"control_wait","next":null,"parent":"%R)9:Xk-@-=M:l:,t~X#","inputs":{"DURATION":[1,[5,"0.2"]]},"fields":{},"shadow":false,"topLevel":false}},"comments":{},"currentCostume":0,"costumes":[{"assetId":"3525966db57e6b3fe88ee7c76c9d81bc","name":"ballerina-a","bitmapResolution":1,"md5ext":"3525966db57e6b3fe88ee7c76c9d81bc.svg","dataFormat":"svg","rotationCenterX":75,"rotationCenterY":75},{"assetId":"7d52bc58acf7d29a4807ab8270d9c262","name":"ballerina-b","bitmapResolution":1,"md5ext":"7d52bc58acf7d29a4807ab8270d9c262.svg","dataFormat":"svg","rotationCenterX":75,"rotationCenterY":75},{"assetId":"2b6c5d8c5193f8c78c8b7e929a6128a4","name":"ballerina-c","bitmapResolution":1,"md5ext":"2b6c5d8c5193f8c78c8b7e929a6128a4.svg","dataFormat":"svg","rotationCenterX":75,"rotationCenterY":75},{"assetId":"79d1a9ee514fa4b952eddf9f4990eca8","name":"ballerina-d","bitmapResolution":1,"md5ext":"79d1a9ee514fa4b952eddf9f4990eca8.svg","dataFormat":"svg","rotationCenterX":75,"rotationCenterY":75}],"sounds":[{"assetId":"83a9787d4cb6f3b7632b4ddfebf74367","name":"pop","dataFormat":"wav","format":"","rate":44100,"sampleCount":1032,"md5ext":"83a9787d4cb6f3b7632b4ddfebf74367.wav"}],"volume":100,"layerOrder":4,"visible":true,"x":55,"y":-90,"size":100,"direction":90,"draggable":false,"rotationStyle":"all around"}],"monitors":[],"extensions":[],"meta":{"semver":"3.0.0","vm":"0.2.0-prerelease.20190417203423","agent":"Mozilla/5.0 (Macintosh; Intel Mac OS X 10_9_5) AppleWebKit/537.36 (KHTML, like Gecko) Chrome/65.0.3325.181 Safari/537.36"}}