{"targets":[{"isStage":true,"name":"Stage","variables":{"`jEk@4|i[#Fk?(8x)AV.-my variable":["my variable",0]},"lists":{},"broadcasts":{},"blocks":{},"comments":{},"currentCostume":1,"costumes":[{"assetId":"cd21514d0531fdffb22204e0ec5ed84a","name":"backdrop1","md5ext":"cd21514d0531fdffb22204e0ec5ed84a.svg","dataFormat":"svg","rotationCenterX":240,"rotationCenterY":180},{"assetId":"05ae3e3bbea890a6e3552ffe8456775e","name":"Room 2","bitmapResolution":2,"md5ext":"05ae3e3bbea890a6e3552ffe8456775e.png","dataFormat":"png","rotationCenterX":480,"rotationCenterY":360},{"assetId":"a81668321aa3dcc0fc185d3e36ae76f6","name":"Room 1","bitmapResolution":2,"md5ext":"a81668321aa3dcc0fc185d3e36ae76f6.png","dataFormat":"png","rotationCenterX":480,"rotationCenterY":360}],"sounds":[{"assetId":"83a9787d4cb6f3b7632b4ddfebf74367","name":"pop","dataFormat":"wav","format":"","rate":48000,"sampleCount":1123,"md5ext":"83a9787d4cb6f3b7632b4ddfebf74367.wav"}],"volume":100,"layerOrder":0,"tempo":60,"videoTransparency":50,"videoState":"on","textToSpeechLanguage":null},{"isStage":false,"name":"Princess","variables":{},"lists":{},"broadcasts":{},"blocks":{"fZZP|^(jU46?6=T~_zE`":{"opcode":"looks_sayforsecs","next":"lnOUH|Ujf:oJ-G:l+J8+","parent":"=Ve$(JG0E:VJDPe7b{Ey","inputs":{"MESSAGE":[1,[10,"Where are all those freakin eggs"]],"SECS":[1,[4,"3"]]},"fields":{},"shadow":false,"topLevel":false},"=Ve$(JG0E:VJDPe7b{Ey":{"opcode":"event_whenflagclicked","next":"fZZP|^(jU46?6=T~_zE`","parent":null,"inputs":{},"fields":{},"shadow":false,"topLevel":true,"x":87,"y":199},"BEpwQtMZHKC*[tGt?o=2":{"opcode":"looks_nextcostume","next":null,"parent":"rDGy|KF{Os_m1k,4H6,K","inputs":{},"fields":{},"shadow":false,"topLevel":false},"lnOUH|Ujf:oJ-G:l+J8+":{"opcode":"control_repeat","next":null,"parent":"fZZP|^(jU46?6=T~_zE`","inputs":{"TIMES":[1,[6,"60"]],"SUBSTACK":[2,"rDGy|KF{Os_m1k,4H6,K"]},"fields":{},"shadow":false,"topLevel":false},"rDGy|KF{Os_m1k,4H6,K":{"opcode":"control_wait","next":"BEpwQtMZHKC*[tGt?o=2","parent":"lnOUH|Ujf:oJ-G:l+J8+","inputs":{"DURATION":[1,[5,"0"]]},"fields":{},"shadow":false,"topLevel":false}},"comments":{},"currentCostume":1,"costumes":[{"assetId":"ca5f59f4f148e2b25a778b4868f67605","name":"princess-b","bitmapResolution":1,"md5ext":"ca5f59f4f148e2b25a778b4868f67605.svg","dataFormat":"svg","rotationCenterX":66,"rotationCenterY":131.99960680313276},{"assetId":"7c2b506449e4593e90a2dd36c2084e1a","name":"princess-c","bitmapResolution":1,"md5ext":"7c2b506449e4593e90a2dd36c2084e1a.svg","dataFormat":"svg","rotationCenterX":66,"rotationCenterY":131.99960840156638},{"assetId":"b8409079d6292a0590da1b41565a52ec","name":"princess-d","bitmapResolution":1,"md5ext":"b8409079d6292a0590da1b41565a52ec.svg","dataFormat":"svg","rotationCenterX":66,"rotationCenterY":131.99960840156638},{"assetId":"3a6ec6bdf31bd26be5bb935d4ab1ace6","name":"princess-e","bitmapResolution":1,"md5ext":"3a6ec6bdf31bd26be5bb935d4ab1ace6.svg","dataFormat":"svg","rotationCenterX":65.9,"rotationCenterY":131.99960840156638}],"sounds":[{"assetId":"1cb60ecdb1075c8769cb346d5c2a22c7","name":"magic spell","dataFormat":"wav","format":"adpcm","rate":22050,"sampleCount":43689,"md5ext":"1cb60ecdb1075c8769cb346d5c2a22c7.wav"}],"volume":100,"layerOrder":2,"visible":true,"x":-88,"y":-93,"size":70,"direction":90,"draggable":false,"rotationStyle":"all around"},{"isStage":false,"name":"Mermaid","variables":{},"lists":{},"broadcasts":{},"blocks":{")0XO)oDRBc`mv8xjaQ.a":{"opcode":"looks_sayforsecs","next":"JevCL6!Jo.A#dpgZs`o:","parent":"L1:,u4osll]t/X-iZi?_","inputs":{"MESSAGE":[1,[10,"Calm Down"]],"SECS":[1,[4,"7"]]},"fields":{},"shadow":false,"topLevel":false},"L1:,u4osll]t/X-iZi?_":{"opcode":"event_whenflagclicked","next":")0XO)oDRBc`mv8xjaQ.a","parent":null,"inputs":{},"fields":{},"shadow":false,"topLevel":true,"x":84,"y":310},"JevCL6!Jo.A#dpgZs`o:":{"opcode":"looks_nextcostume","next":null,"parent":")0XO)oDRBc`mv8xjaQ.a","inputs":{},"fields":{},"shadow":false,"topLevel":false}},"comments":{},"currentCostume":1,"costumes":[{"assetId":"a2999262667daf4ac8ddc97890d0d36d","name":"mermaid-a","bitmapResolution":1,"md5ext":"a2999262667daf4ac8ddc97890d0d36d.svg","dataFormat":"svg","rotationCenterX":69.99168312861494,"rotationCenterY":115.5},{"assetId":"f624a87983b87d9f0ab532de764f7e18","name":"mermaid-b","bitmapResolution":1,"md5ext":"f624a87983b87d9f0ab532de764f7e18.svg","dataFormat":"svg","rotationCenterX":240,"rotationCenterY":180},{"assetId":"2a6274017350fab67ebec9157420ae96","name":"mermaid-c","bitmapResolution":1,"md5ext":"2a6274017350fab67ebec9157420ae96.svg","dataFormat":"svg","rotationCenterX":150,"rotationCenterY":115},{"assetId":"65419296861b1c7ee59075af0f949d67","name":"mermaid-d","bitmapResolution":1,"md5ext":"65419296861b1c7ee59075af0f949d67.svg","dataFormat":"svg","rotationCenterX":150,"rotationCenterY":115}],"sounds":[{"assetId":"c904610d770398b98872a708a2f75611","name":"ocean wave","dataFormat":"wav","format":"adpcm","rate":22050,"sampleCount":99569,"md5ext":"c904610d770398b98872a708a2f75611.wav"}],"volume":100,"layerOrder":1,"visible":true,"x":-210,"y":-45.00000000000001,"size":100,"direction":90,"draggable":false,"rotationStyle":"all around"},{"isStage":false,"name":"Egg","variables":{},"lists":{},"broadcasts":{},"blocks":{"XivaSmzp(f85D+|WyT1j":{"opcode":"event_whenkeypressed","next":"YffJlzdn5!Z}vT(/+O^d","parent":null,"inputs":{},"fields":{"KEY_OPTION":["any",null]},"shadow":false,"topLevel":true,"x":87,"y":206},")yckeD#p.+Isz0HJ..Mi":{"opcode":"looks_sayforsecs","next":"q_M!dhhM:j5j-o]|s7g(","parent":"YffJlzdn5!Z}vT(/+O^d","inputs":{"MESSAGE":[1,[10,"I got you  this egg"]],"SECS":[1,[4,"2"]]},"fields":{},"shadow":false,"topLevel":false},"q_M!dhhM:j5j-o]|s7g(":{"opcode":"looks_sayforsecs","next":"th)FZQV/aH~c{Ey:nGm?","parent":")yckeD#p.+Isz0HJ..Mi","inputs":{"MESSAGE":[1,[10,"Cool Right"]],"SECS":[1,[4,"2"]]},"fields":{},"shadow":false,"topLevel":false},"YffJlzdn5!Z}vT(/+O^d":{"opcode":"looks_setsizeto","next":")yckeD#p.+Isz0HJ..Mi","parent":"XivaSmzp(f85D+|WyT1j","inputs":{"SIZE":[1,[4,"50"]]},"fields":{},"shadow":false,"topLevel":false},"th)FZQV/aH~c{Ey:nGm?":{"opcode":"looks_setsizeto","next":null,"parent":"q_M!dhhM:j5j-o]|s7g(","inputs":{"SIZE":[1,[4,"400"]]},"fields":{},"shadow":false,"topLevel":false}},"comments":{},"currentCostume":0,"costumes":[{"assetId":"d9376dac04ace6926882cc65d4e7d43a","name":"egg-a","bitmapResolution":1,"md5ext":"d9376dac04ace6926882cc65d4e7d43a.svg","dataFormat":"svg","rotationCenterX":20,"rotationCenterY":27.5},{"assetId":"fbc629c3b062423e8c09cfacfb1e65f8","name":"egg-b","bitmapResolution":1,"md5ext":"fbc629c3b062423e8c09cfacfb1e65f8.svg","dataFormat":"svg","rotationCenterX":23,"rotationCenterY":27},{"assetId":"0d127490af16f8a4ca5ce3212b2391c2","name":"egg-c","bitmapResolution":1,"md5ext":"0d127490af16f8a4ca5ce3212b2391c2.svg","dataFormat":"svg","rotationCenterX":28,"rotationCenterY":27},{"assetId":"b0b6e88ec64b842398200bab562b53e3","name":"egg-d","bitmapResolution":1,"md5ext":"b0b6e88ec64b842398200bab562b53e3.svg","dataFormat":"svg","rotationCenterX":19,"rotationCenterY":27},{"assetId":"41535b4742f40e2630746b0c4bec98f2","name":"egg-e","bitmapResolution":1,"md5ext":"41535b4742f40e2630746b0c4bec98f2.svg","dataFormat":"svg","rotationCenterX":20,"rotationCenterY":26},{"assetId":"bb0505b802140a8cc200c9f8bfce4503","name":"egg-f","bitmapResolution":1,"md5ext":"bb0505b802140a8cc200c9f8bfce4503.svg","dataFormat":"svg","rotationCenterX":31,"rotationCenterY":26}],"sounds":[{"assetId":"83a9787d4cb6f3b7632b4ddfebf74367","name":"pop","dataFormat":"wav","format":"","rate":48000,"sampleCount":1123,"md5ext":"83a9787d4cb6f3b7632b4ddfebf74367.wav"}],"volume":100,"layerOrder":4,"visible":true,"x":13,"y":-59.000000000000014,"size":400,"direction":90,"draggable":false,"rotationStyle":"all around"},{"isStage":false,"name":"Hannah","variables":{},"lists":{},"broadcasts":{},"blocks":{"h!Wg87=pvL!y#XLKcDDt":{"opcode":"event_whenkeypressed","next":"*xdEacP{PV!=_T69b0Yb","parent":null,"inputs":{},"fields":{"KEY_OPTION":["any"]},"shadow":false,"topLevel":true,"x":87,"y":207},"*xdEacP{PV!=_T69b0Yb":{"opcode":"looks_sayforsecs","next":"YZ7BFel|HL?eS*ung6^]","parent":"h!Wg87=pvL!y#XLKcDDt","inputs":{"MESSAGE":[1,[10,"I got you  this egg"]],"SECS":[1,[4,"2"]]},"fields":{},"shadow":false,"topLevel":false},"YZ7BFel|HL?eS*ung6^]":{"opcode":"looks_sayforsecs","next":null,"parent":"*xdEacP{PV!=_T69b0Yb","inputs":{"MESSAGE":[1,[10,"Cool Right"]],"SECS":[1,[4,"2"]]},"fields":{},"shadow":false,"topLevel":false},"EH]`_A%}[APxx9l2djQ-":{"opcode":"looks_setsizeto","next":null,"parent":"QE,mFc;S9q*[x6ii!z0w","inputs":{"SIZE":[1,[4,"120"]]},"fields":{},"shadow":false,"topLevel":false},"QE,mFc;S9q*[x6ii!z0w":{"opcode":"event_whenflagclicked","next":"EH]`_A%}[APxx9l2djQ-","parent":null,"inputs":{},"fields":{},"shadow":false,"topLevel":true,"x":203,"y":-49}},"comments":{},"currentCostume":1,"costumes":[{"assetId":"18989509a97de0608cf60a90023a24ef","name":"hannah-a","bitmapResolution":1,"md5ext":"18989509a97de0608cf60a90023a24ef.svg","dataFormat":"svg","rotationCenterX":69,"rotationCenterY":63},{"assetId":"5f1a4e9a47cd0958eb07ae06c5b6b32c","name":"hannah-b","bitmapResolution":2,"md5ext":"5f1a4e9a47cd0958eb07ae06c5b6b32c.png","dataFormat":"png","rotationCenterX":55,"rotationCenterY":173}],"sounds":[{"assetId":"83a9787d4cb6f3b7632b4ddfebf74367","name":"pop","dataFormat":"wav","format":"","rate":48000,"sampleCount":1123,"md5ext":"83a9787d4cb6f3b7632b4ddfebf74367.wav"}],"volume":100,"layerOrder":3,"visible":true,"x":106,"y":-86,"size":120,"direction":90,"draggable":false,"rotationStyle":"all around"}],"monitors":[],"extensions":[],"meta":{"semver":"3.0.0","vm":"0.2.0-prerelease.20190321151527","agent":"Mozilla/5.0 (Windows NT 10.0; Win64; x64) AppleWebKit/537.36 (KHTML, like Gecko) Chrome/68.0.3440.84 Safari/537.36"}}